annotated_text/__init__.py
annotated_text/parameters.py
annotated_text/util.py
st_annotated_text-4.0.1.dist-info/LICENSE
st_annotated_text-4.0.1.dist-info/METADATA
st_annotated_text-4.0.1.dist-info/WHEEL
st_annotated_text-4.0.1.dist-info/top_level.txt
st_annotated_text-4.0.1.dist-info/RECORD
