Metadata-Version: 2.1
Name: st-annotated-text
Version: 4.0.1
Summary: A simple component to display annotated text in Streamlit apps.
Home-page: https://github.com/tvst/st-annotated-text
Author: Thiago Teixeira
Author-email: me@thiagot.com
License: Apache 2
Classifier: Programming Language :: Python :: 3
Classifier: License :: OSI Approved :: Apache Software License
Classifier: Operating System :: OS Independent
Requires-Python: >=3.5
License-File: LICENSE
